gumo/__init__.py
gumo/task/__init__.py
gumo/task/_configuration.py
gumo/task/bind.py
gumo/task/application/__init__.py
gumo/task/application/factory.py
gumo/task/application/repository.py
gumo/task/domain/__init__.py
gumo/task/framework/__init__.py
gumo/task/infrastructure/__init__.py
gumo/task/infrastructure/cloud_tasks/__init__.py
gumo/task/infrastructure/configuration/__init__.py
gumo/task/infrastructure/repository/__init__.py
gumo/task/infrastructure/repository/mapper.py
gumo_task-0.3.2.dist-info/LICENSE
gumo_task-0.3.2.dist-info/METADATA
gumo_task-0.3.2.dist-info/WHEEL
gumo_task-0.3.2.dist-info/top_level.txt
gumo_task-0.3.2.dist-info/RECORD
